STRIDE/Clustering.py
STRIDE/Deconvolution.py
STRIDE/Integration.py
STRIDE/Mapping.py
STRIDE/ModelEvaluate.py
STRIDE/ModelTrain.py
STRIDE/Plot.py
STRIDE/__init__.py
STRIDE/version.py
STRIDE/version.txt
STRIDE/utility/IO.py
STRIDE/utility/MarkerFind.py
STRIDE/utility/ParameterValidate.py
STRIDE/utility/__init__.py
stridespatial-0.0.2b0.data/scripts/STRIDE
utility/IO.py
utility/MarkerFind.py
utility/ParameterValidate.py
utility/__init__.py
stridespatial-0.0.2b0.dist-info/LICENSE
stridespatial-0.0.2b0.dist-info/METADATA
stridespatial-0.0.2b0.dist-info/WHEEL
stridespatial-0.0.2b0.dist-info/top_level.txt
stridespatial-0.0.2b0.dist-info/RECORD
