Metadata-Version: 2.1
Name: stridespatial
Version: 0.0.2b0
Summary: STRIDE (Spatial TRanscrIptomics DEconvolution by topic modelling) is a cell-type deconvolution tool for spatial transcriptomics. 
Home-page: https://github.com/dongqingsun96/STRIDE
Author: Dongqing Sun
Author-email: Dongqing Sun <dongqingsun96@gmail.com>
License: GNU GENERAL PUBLIC LICENSE
Project-URL: Homepage, https://pypi.org/project/stridespatial/
Project-URL: Bug Tracker, https://github.com/wanglabtongji/STRIDE/issues
Classifier: Development Status :: 4 - Beta
Classifier: Environment :: Console
Classifier: Intended Audience :: Science/Research
Classifier: License :: OSI Approved :: GNU General Public License v3 (GPLv3)
Classifier: Natural Language :: English
Classifier: Programming Language :: Python :: 3
Classifier: Topic :: Scientific/Engineering :: Bio-Informatics
Requires-Python: >=3.7
License-File: LICENSE
Requires-Dist: Cython
Requires-Dist: numpy (>=1.20.3)
Requires-Dist: gensim (==3.8.3)
Requires-Dist: scikit-learn (>=0.24)
Requires-Dist: pandas (>=1.1.4)
Requires-Dist: scipy (>=1.6.3)
Requires-Dist: matplotlib (>=3.3.3)
Requires-Dist: seaborn (>=0.11.1)
Requires-Dist: scanpy (>=1.6.0)
Requires-Dist: h5py (>=2.10.0)
Requires-Dist: tables (>=3.6.1)
Requires-Dist: pot (>=0.7.0)
